liuzh594Crypto/__init__.py
liuzh594Crypto/basicMath/ECC.py
liuzh594Crypto/basicMath/GF.py
liuzh594Crypto/basicMath/__init__.py
liuzh594Crypto/basicMath/basic.py
liuzh594Crypto/basicMath/type.py
liuzh594Crypto/blockCipher/SM4.py
liuzh594Crypto/blockCipher/__init__.py
liuzh594Crypto/digitalSignature/SM2_SV.py
liuzh594Crypto/digitalSignature/__init__.py
liuzh594Crypto/hash/SM3.py
liuzh594Crypto/hash/__init__.py
liuzh594Crypto/pubkeyCipher/RSA.py
liuzh594Crypto/pubkeyCipher/SM2.py
liuzh594Crypto/pubkeyCipher/__init__.py
liuzh594Crypto/tests/__init__.py
liuzh594Crypto/tests/tests.py
liuzh594Crypto-5.9.4.999.99.dist-info/LICENSE
liuzh594Crypto-5.9.4.999.99.dist-info/METADATA
liuzh594Crypto-5.9.4.999.99.dist-info/WHEEL
liuzh594Crypto-5.9.4.999.99.dist-info/top_level.txt
liuzh594Crypto-5.9.4.999.99.dist-info/RECORD
