Metadata-Version: 2.1
Name: liuzh594Crypto
Version: 5.9.4.999.99
Summary: my crypto python package in 2023
Home-page: https://github.com/lzh594/liuzh594Crypto
Author: Liuzhenghao
Author-email: liuzh594@qq.com
Classifier: Programming Language :: Python :: 3
Classifier: Programming Language :: Python :: 3.7
Classifier: Programming Language :: Python :: 3.8
Classifier: Programming Language :: Python :: 3.9
Classifier: Programming Language :: Python :: 3.10
Classifier: Programming Language :: Python :: 3 :: Only
Classifier: License :: OSI Approved :: MIT License
Classifier: Operating System :: OS Independent
License-File: LICENSE
